pyats_genie_command_parse/__init__.py
pyats_genie_command_parse/pyats_genie_command_parse.py
pyats_genie_command_parse/version.py
pyats_genie_command_parse-1.4.4.dist-info/licenses/LICENSE
pyats_genie_command_parse-1.4.4.dist-info/METADATA
pyats_genie_command_parse-1.4.4.dist-info/WHEEL
pyats_genie_command_parse-1.4.4.dist-info/top_level.txt
pyats_genie_command_parse-1.4.4.dist-info/RECORD
