Metadata-Version: 2.4
Name: pyats-genie-command-parse
Version: 1.4.4
Summary: Run genie parsers directly.
Author-email: "Benjamin P. Trachtenberg" <e_ben_75-python@yahoo.com>, Brett Gianpetro <e_ben_75-python@yahoo.com>
Maintainer-email: "Benjamin P. Trachtenberg" <e_ben_75-python@yahoo.com>
License-Expression: MIT
Project-URL: Documentation, https://pyats-genie-command-parse.readthedocs.io/en/latest/
Project-URL: Source, https://github.com/btr1975/pyats-genie-command-parse
Project-URL: Tracker, https://github.com/btr1975/pyats-genie-command-parse/issues
Keywords: pyATS,genie,cisco,ios,ios-xr,nxos,parse,wrapper
Classifier: Development Status :: 5 - Production/Stable
Classifier: Intended Audience :: Developers
Classifier: Natural Language :: English
Classifier: Operating System :: POSIX
Classifier: Operating System :: POSIX :: BSD
Classifier: Operating System :: POSIX :: Linux
Classifier: Programming Language :: Python :: 3
Classifier: Programming Language :: Python :: 3 :: Only
Classifier: Programming Language :: Python :: 3.9
Classifier: Programming Language :: Python :: 3.10
Classifier: Programming Language :: Python :: 3.11
Classifier: Programming Language :: Python :: 3.12
Classifier: Programming Language :: Python :: 3.13
Requires-Python: >=3.9
License-File: LICENSE
Requires-Dist: genie==25.7
Requires-Dist: pyats==25.7
Dynamic: license-file
